Metadata-Version: 2.1
Name: kbhmap
Version: 0.5.5
Summary: UNKNOWN
Home-page: https://github.com/pranphy/KeyboardHeatmap
Author: Prakash Gautam
Author-email: info@pgautam.com.np
License: UNKNOWN
Platform: UNKNOWN
Classifier: Programming Language :: Python :: 3
Classifier: Operating System :: OS Independent
